barocert/__init__.py
barocert/base.py
barocert/kakaocertService.py
barocert-1.0.2.dist-info/LICENSE.md
barocert-1.0.2.dist-info/METADATA
barocert-1.0.2.dist-info/WHEEL
barocert-1.0.2.dist-info/top_level.txt
barocert-1.0.2.dist-info/RECORD
