Metadata-Version: 2.1
Name: barocert
Version: 1.0.2
Summary: barocert API SDK Library
Home-page: https://github.com/barocert/barocert.py
Download-URL: https://github.com/barocert/barocert.py/archive/1.0.2.tar.gz
Author: linkhub dev
Author-email: dev@linkhubcorp.com
License: MIT
Platform: Posix; MacOS X; Windows
Classifier: Development Status :: 5 - Production/Stable
Classifier: Intended Audience :: Developers
Classifier: License :: OSI Approved :: MIT License
Classifier: Operating System :: OS Independent
Classifier: Topic :: Internet
Classifier: Programming Language :: Python :: 2
Classifier: Programming Language :: Python :: 2.6
Classifier: Programming Language :: Python :: 2.7
Classifier: Programming Language :: Python :: 3
Classifier: Programming Language :: Python :: 3.3
Classifier: Programming Language :: Python :: 3.4
Classifier: Programming Language :: Python :: 3.5
Classifier: Programming Language :: Python :: 3.6
Classifier: Programming Language :: Python :: 3.7
License-File: LICENSE.md
Requires-Dist: linkhub
